jupyter_openbis_integration_service/__init__.py
jupyter_openbis_integration_service/server.py
jupyter_openbis_integration_service-0.2.5.dist-info/DESCRIPTION.rst
jupyter_openbis_integration_service-0.2.5.dist-info/METADATA
jupyter_openbis_integration_service-0.2.5.dist-info/RECORD
jupyter_openbis_integration_service-0.2.5.dist-info/WHEEL
jupyter_openbis_integration_service-0.2.5.dist-info/entry_points.txt
jupyter_openbis_integration_service-0.2.5.dist-info/metadata.json
jupyter_openbis_integration_service-0.2.5.dist-info/top_level.txt
