Metadata-Version: 2.0
Name: jupyter-openbis-integration-service
Version: 0.2.5
Summary: A webservice to create jupyter notebooks in the users home directory
Home-page: https://sissource.ethz.ch/sis/jupyter-openbis-integration/
Author: SIS | ID | ETH Zuerich
Author-email: swen@ethz.ch
License: BSD
Platform: UNKNOWN
Requires-Dist: tornado
